pyemail_sender/__init__.py
pyemail_sender/abstract_pyemail_sender.py
pyemail_sender/gmail_pyemail_sender.py
pyemail_sender/pyemail_sender_config.py
pyemail_sender/pyemail_sender_schema.json
pyemail_sender-1.0.1.data/data/pyemail_sender_schema.json
tests/__init__.py
tests/test_gmail_pyemail_sender.py
pyemail_sender-1.0.1.dist-info/LICENSE
pyemail_sender-1.0.1.dist-info/METADATA
pyemail_sender-1.0.1.dist-info/WHEEL
pyemail_sender-1.0.1.dist-info/entry_points.txt
pyemail_sender-1.0.1.dist-info/top_level.txt
pyemail_sender-1.0.1.dist-info/RECORD
