Metadata-Version: 2.1
Name: pyemail-sender
Version: 1.0.1
Summary: A utility for sending emails with attachments. Currently only Gmail is supported.
Home-page: https://github.com/drkostas/pyemail-sender/tree/master/
Author: Kostas Georgiou
Author-email: georgiou.kostas94@gmail.com
License: Apache Software License 2.0
Keywords: email,emailer,email-sender,attachments,gmail
Platform: UNKNOWN
Classifier: Development Status :: 5 - Production/Stable
Classifier: Intended Audience :: Developers
Classifier: License :: OSI Approved :: Apache Software License
Classifier: Natural Language :: English
Classifier: Programming Language :: Python :: 3.6
Classifier: Programming Language :: Python :: 3.7
Classifier: Programming Language :: Python :: 3.8
Requires-Python: >=3.6
License-File: LICENSE
Requires-Dist: gmail (>=0.6.3)
Requires-Dist: yaml-config-wrapper (>=1.0.4)
Requires-Dist: termcolor-logger (>=1.0.3)
